{
    "asset": {
        "format": "png",
        "id": "07d02186d4a5a44fa88e17ba3a889e08",
        "name": "ffxiv_20230223_004246_968.png",
        "path": "file:D:/workspace/github/gelehrte-languageecho/image-FF14-letters/input/ffxiv_20230223_004246_968.png",
        "size": {
            "width": 1920,
            "height": 1080
        },
        "state": 2,
        "type": 1
    },
    "regions": [
        {
            "id": "Kv-_xgvhQ",
            "type": "RECTANGLE",
            "tags": [
                "letters"
            ],
            "boundingBox": {
                "height": 78.04195804195804,
                "width": 251.63826998689385,
                "left": 685.7142857142858,
                "top": 35.48076923076923
            },
            "points": [
                {
                    "x": 685.7142857142858,
                    "y": 35.48076923076923
                },
                {
                    "x": 937.3525557011795,
                    "y": 35.48076923076923
                },
                {
                    "x": 937.3525557011795,
                    "y": 113.52272727272728
                },
                {
                    "x": 685.7142857142858,
                    "y": 113.52272727272728
                }
            ]
        },
        {
            "id": "58-LjIFrU",
            "type": "RECTANGLE",
            "tags": [
                "letters"
            ],
            "boundingBox": {
                "height": 229.0909090909091,
                "width": 729.7509829619921,
                "left": 445.39973787680213,
                "top": 93.38286713286713
            },
            "points": [
                {
                    "x": 445.39973787680213,
                    "y": 93.38286713286713
                },
                {
                    "x": 1175.1507208387943,
                    "y": 93.38286713286713
                },
                {
                    "x": 1175.1507208387943,
                    "y": 322.4737762237762
                },
                {
                    "x": 445.39973787680213,
                    "y": 322.4737762237762
                }
            ]
        }
    ],
    "version": "2.2.0"
}