{
    "asset": {
        "format": "png",
        "id": "1c548c433508ec925355e96dc543bf25",
        "name": "ffxiv_20221029_022310_007.png",
        "path": "file:D:/workspace/github/gelehrte-languageecho/image-FF14-letters/input/ffxiv_20221029_022310_007.png",
        "size": {
            "width": 1920,
            "height": 1080
        },
        "state": 2,
        "type": 1
    },
    "regions": [
        {
            "id": "AYuc8ZPP9",
            "type": "RECTANGLE",
            "tags": [
                "letters_r_90"
            ],
            "boundingBox": {
                "height": 1004.0524433849822,
                "width": 311.4209115281501,
                "left": 1132.4396782841823,
                "top": 22.687723480333734
            },
            "points": [
                {
                    "x": 1132.4396782841823,
                    "y": 22.687723480333734
                },
                {
                    "x": 1443.8605898123324,
                    "y": 22.687723480333734
                },
                {
                    "x": 1443.8605898123324,
                    "y": 1026.740166865316
                },
                {
                    "x": 1132.4396782841823,
                    "y": 1026.740166865316
                }
            ]
        }
    ],
    "version": "2.2.0"
}